[{"TeamID":1610612764,"SEASON":"2022","LeagueID":"00","PLAYER":"Johnny Davis","NICKNAME":"Johnny","PLAYER_SLUG":"johnny-davis","NUM":"1","POSITION":"G","HEIGHT":"6-4","WEIGHT":"195","BIRTH_DATE":"FEB 27, 2002","AGE":21.0,"EXP":"R","SCHOOL":"Wisconsin","PLAYER_ID":1631098,"HOW_ACQUIRED":null},{"TeamID":1610612764,"SEASON":"2022","LeagueID":"00","PLAYER":"Bradley Beal","NICKNAME":"Bradley","PLAYER_SLUG":"bradley-beal","NUM":"3","POSITION":"G","HEIGHT":"6-4","WEIGHT":"207","BIRTH_DATE":"JUN 28, 1993","AGE":30.0,"EXP":"10","SCHOOL":"Florida","PLAYER_ID":203078,"HOW_ACQUIRED":null},{"TeamID":1610612764,"SEASON":"2022","LeagueID":"00","PLAYER":"Kristaps Porzi\u0146\u0123is","NICKNAME":"Kristaps","PLAYER_SLUG":"kristaps-porzi\u0146\u0123is","NUM":"6","POSITION":"F-C","HEIGHT":"7-3","WEIGHT":"240","BIRTH_DATE":"AUG 02, 1995","AGE":27.0,"EXP":"7","SCHOOL":"Cajasol Sevilla","PLAYER_ID":204001,"HOW_ACQUIRED":null},{"TeamID":1610612764,"SEASON":"2022","LeagueID":"00","PLAYER":"Jordan Goodwin","NICKNAME":"Jordan","PLAYER_SLUG":"jordan-goodwin","NUM":"7","POSITION":"G","HEIGHT":"6-3","WEIGHT":"200","BIRTH_DATE":"OCT 23, 1998","AGE":24.0,"EXP":"1","SCHOOL":"St. Louis","PLAYER_ID":1630692,"HOW_ACQUIRED":null},{"TeamID":1610612764,"SEASON":"2022","LeagueID":"00","PLAYER":"Deni Avdija","NICKNAME":"Deni","PLAYER_SLUG":"deni-avdija","NUM":"9","POSITION":"F","HEIGHT":"6-9","WEIGHT":"210","BIRTH_DATE":"JAN 03, 2001","AGE":22.0,"EXP":"2","SCHOOL":"Maccabi Tel Aviv","PLAYER_ID":1630166,"HOW_ACQUIRED":null},{"TeamID":1610612764,"SEASON":"2022","LeagueID":"00","PLAYER":"Xavier Cooks","NICKNAME":"Xavier","PLAYER_SLUG":"xavier-cooks","NUM":"12","POSITION":"F","HEIGHT":"6-8","WEIGHT":"183","BIRTH_DATE":"AUG 19, 1995","AGE":27.0,"EXP":"R","SCHOOL":"Winthrop","PLAYER_ID":1641645,"HOW_ACQUIRED":null},{"TeamID":1610612764,"SEASON":"2022","LeagueID":"00","PLAYER":"Isaiah Todd","NICKNAME":"Isaiah","PLAYER_SLUG":"isaiah-todd","NUM":"14","POSITION":"F","HEIGHT":"6-9","WEIGHT":"219","BIRTH_DATE":"OCT 17, 2001","AGE":21.0,"EXP":"1","SCHOOL":"G League Ignite","PLAYER_ID":1630225,"HOW_ACQUIRED":null},{"TeamID":1610612764,"SEASON":"2022","LeagueID":"00","PLAYER":"Anthony Gill","NICKNAME":"Anthony","PLAYER_SLUG":"anthony-gill","NUM":"16","POSITION":"F","HEIGHT":"6-8","WEIGHT":"230","BIRTH_DATE":"OCT 17, 1992","AGE":30.0,"EXP":"2","SCHOOL":"Virginia","PLAYER_ID":1630264,"HOW_ACQUIRED":"Signed on 11\/30\/20"},{"TeamID":1610612764,"SEASON":"2022","LeagueID":"00","PLAYER":"Kendrick Nunn","NICKNAME":"Kendrick","PLAYER_SLUG":"kendrick-nunn","NUM":"20","POSITION":"G","HEIGHT":"6-3","WEIGHT":"190","BIRTH_DATE":"AUG 03, 1995","AGE":27.0,"EXP":"2","SCHOOL":"Oakland","PLAYER_ID":1629134,"HOW_ACQUIRED":null},{"TeamID":1610612764,"SEASON":"2022","LeagueID":"00","PLAYER":"Daniel Gafford","NICKNAME":"Daniel","PLAYER_SLUG":"daniel-gafford","NUM":"21","POSITION":"F-C","HEIGHT":"6-10","WEIGHT":"234","BIRTH_DATE":"OCT 01, 1998","AGE":24.0,"EXP":"3","SCHOOL":"Arkansas","PLAYER_ID":1629655,"HOW_ACQUIRED":null},{"TeamID":1610612764,"SEASON":"2022","LeagueID":"00","PLAYER":"Mont\u00e9 Morris","NICKNAME":"Mont\u00e9","PLAYER_SLUG":"mont\u00e9-morris","NUM":"22","POSITION":"G","HEIGHT":"6-2","WEIGHT":"183","BIRTH_DATE":"JUN 27, 1995","AGE":28.0,"EXP":"5","SCHOOL":"Iowa State","PLAYER_ID":1628420,"HOW_ACQUIRED":null},{"TeamID":1610612764,"SEASON":"2022","LeagueID":"00","PLAYER":"Corey Kispert","NICKNAME":"Corey","PLAYER_SLUG":"corey-kispert","NUM":"24","POSITION":"F","HEIGHT":"6-6","WEIGHT":"224","BIRTH_DATE":"MAR 03, 1999","AGE":24.0,"EXP":"1","SCHOOL":"Gonzaga","PLAYER_ID":1630557,"HOW_ACQUIRED":"#15 Pick in 2021 Draft"},{"TeamID":1610612764,"SEASON":"2022","LeagueID":"00","PLAYER":"Quenton Jackson","NICKNAME":"Quenton","PLAYER_SLUG":"quenton-jackson","NUM":"29","POSITION":"G","HEIGHT":"6-5","WEIGHT":"173","BIRTH_DATE":"SEP 15, 1998","AGE":24.0,"EXP":"R","SCHOOL":"Texas A&M","PLAYER_ID":1631245,"HOW_ACQUIRED":null},{"TeamID":1610612764,"SEASON":"2022","LeagueID":"00","PLAYER":"Kyle Kuzma","NICKNAME":"Kyle","PLAYER_SLUG":"kyle-kuzma","NUM":"33","POSITION":"F","HEIGHT":"6-9","WEIGHT":"221","BIRTH_DATE":"JUL 24, 1995","AGE":27.0,"EXP":"5","SCHOOL":"Utah","PLAYER_ID":1628398,"HOW_ACQUIRED":null},{"TeamID":1610612764,"SEASON":"2022","LeagueID":"00","PLAYER":"Jay Huff","NICKNAME":"Jay","PLAYER_SLUG":"jay-huff","NUM":"34","POSITION":"C","HEIGHT":"7-1","WEIGHT":"240","BIRTH_DATE":"AUG 25, 1997","AGE":25.0,"EXP":"1","SCHOOL":"Virginia","PLAYER_ID":1630643,"HOW_ACQUIRED":null},{"TeamID":1610612764,"SEASON":"2022","LeagueID":"00","PLAYER":"Delon Wright","NICKNAME":"Delon","PLAYER_SLUG":"delon-wright","NUM":"55","POSITION":"G","HEIGHT":"6-5","WEIGHT":"185","BIRTH_DATE":"APR 26, 1992","AGE":31.0,"EXP":"7","SCHOOL":"Utah","PLAYER_ID":1626153,"HOW_ACQUIRED":null},{"TeamID":1610612764,"SEASON":"2022","LeagueID":"00","PLAYER":"Taj Gibson","NICKNAME":"Taj","PLAYER_SLUG":"taj-gibson","NUM":"67","POSITION":"F","HEIGHT":"6-9","WEIGHT":"232","BIRTH_DATE":"JUN 24, 1985","AGE":38.0,"EXP":"13","SCHOOL":"Southern California","PLAYER_ID":201959,"HOW_ACQUIRED":null}]