[{"PLAYER_ID":1629670,"SEASON_ID":"2020-21","LEAGUE_ID":"00","TEAM_ID":1610612749,"TEAM_ABBREVIATION":"MIL","PLAYER_AGE":22.0,"GP":30,"GS":2,"MIN":274,"FGM":62,"FGA":135,"FG_PCT":0.459,"FG3M":28,"FG3A":62,"FG3_PCT":0.452,"FTM":19,"FTA":25,"FT_PCT":0.76,"OREB":9,"DREB":51,"REB":60,"AST":7,"STL":17,"BLK":8,"TOV":24,"PF":22,"PTS":171},{"PLAYER_ID":1629670,"SEASON_ID":"2021-22","LEAGUE_ID":"00","TEAM_ID":1610612749,"TEAM_ABBREVIATION":"MIL","PLAYER_AGE":23.0,"GP":62,"GS":13,"MIN":1185,"FGM":186,"FGA":462,"FG_PCT":0.403,"FG3M":79,"FG3A":227,"FG3_PCT":0.348,"FTM":36,"FTA":43,"FT_PCT":0.837,"OREB":37,"DREB":184,"REB":221,"AST":59,"STL":25,"BLK":17,"TOV":57,"PF":78,"PTS":487},{"PLAYER_ID":1629670,"SEASON_ID":"2022-23","LEAGUE_ID":"00","TEAM_ID":1610612749,"TEAM_ABBREVIATION":"MIL","PLAYER_AGE":24.0,"GP":38,"GS":3,"MIN":597,"FGM":76,"FGA":197,"FG_PCT":0.386,"FG3M":40,"FG3A":102,"FG3_PCT":0.392,"FTM":37,"FTA":43,"FT_PCT":0.86,"OREB":29,"DREB":88,"REB":117,"AST":38,"STL":12,"BLK":7,"TOV":34,"PF":34,"PTS":229},{"PLAYER_ID":1629670,"SEASON_ID":"2022-23","LEAGUE_ID":"00","TEAM_ID":1610612754,"TEAM_ABBREVIATION":"IND","PLAYER_AGE":24.0,"GP":24,"GS":11,"MIN":591,"FGM":118,"FGA":248,"FG_PCT":0.476,"FG3M":46,"FG3A":109,"FG3_PCT":0.422,"FTM":31,"FTA":43,"FT_PCT":0.721,"OREB":22,"DREB":90,"REB":112,"AST":50,"STL":12,"BLK":7,"TOV":32,"PF":40,"PTS":313},{"PLAYER_ID":1629670,"SEASON_ID":"2023-24","LEAGUE_ID":"00","TEAM_ID":1610612754,"TEAM_ABBREVIATION":"IND","PLAYER_AGE":25.0,"GP":18,"GS":0,"MIN":183,"FGM":37,"FGA":82,"FG_PCT":0.451,"FG3M":11,"FG3A":36,"FG3_PCT":0.306,"FTM":9,"FTA":11,"FT_PCT":0.818,"OREB":8,"DREB":25,"REB":33,"AST":18,"STL":6,"BLK":1,"TOV":12,"PF":19,"PTS":94},{"PLAYER_ID":1629670,"SEASON_ID":"2023-24","LEAGUE_ID":"00","TEAM_ID":1610612761,"TEAM_ABBREVIATION":"TOR","PLAYER_AGE":25.0,"GP":34,"GS":1,"MIN":529,"FGM":101,"FGA":217,"FG_PCT":0.465,"FG3M":33,"FG3A":95,"FG3_PCT":0.347,"FTM":35,"FTA":42,"FT_PCT":0.833,"OREB":20,"DREB":96,"REB":116,"AST":44,"STL":20,"BLK":12,"TOV":41,"PF":29,"PTS":270}]