[{"PLAYER_ID":1630580,"SEASON_ID":"2021-22","LEAGUE_ID":"00","TEAM_ID":1610612759,"TEAM_ABBREVIATION":"SAS","PLAYER_AGE":22.0,"GP":29,"GS":0,"MIN":205,"FGM":20,"FGA":56,"FG_PCT":0.357,"FG3M":14,"FG3A":43,"FG3_PCT":0.326,"FTM":7,"FTA":13,"FT_PCT":0.538,"OREB":4,"DREB":10,"REB":14,"AST":9,"STL":4,"BLK":3,"TOV":2,"PF":14,"PTS":61},{"PLAYER_ID":1630580,"SEASON_ID":"2022-23","LEAGUE_ID":"00","TEAM_ID":1610612761,"TEAM_ABBREVIATION":"TOR","PLAYER_AGE":23.0,"GP":9,"GS":0,"MIN":50,"FGM":3,"FGA":14,"FG_PCT":0.214,"FG3M":3,"FG3A":12,"FG3_PCT":0.25,"FTM":0,"FTA":0,"FT_PCT":0.0,"OREB":0,"DREB":4,"REB":4,"AST":3,"STL":0,"BLK":0,"TOV":1,"PF":3,"PTS":9}]