[{"PLAYER_ID":1631222,"SEASON_ID":"2022-23","LEAGUE_ID":"00","TEAM_ID":1610612763,"TEAM_ABBREVIATION":"MEM","PLAYER_AGE":21.0,"GP":35,"GS":0,"MIN":414,"FGM":37,"FGA":95,"FG_PCT":0.389,"FG3M":24,"FG3A":71,"FG3_PCT":0.338,"FTM":7,"FTA":9,"FT_PCT":0.778,"OREB":19,"DREB":44,"REB":63,"AST":21,"STL":12,"BLK":4,"TOV":18,"PF":49,"PTS":105},{"PLAYER_ID":1631222,"SEASON_ID":"2023-24","LEAGUE_ID":"00","TEAM_ID":1610612763,"TEAM_ABBREVIATION":"MEM","PLAYER_AGE":22.0,"GP":35,"GS":6,"MIN":806,"FGM":118,"FGA":303,"FG_PCT":0.389,"FG3M":53,"FG3A":156,"FG3_PCT":0.34,"FTM":90,"FTA":109,"FT_PCT":0.826,"OREB":51,"DREB":77,"REB":128,"AST":58,"STL":29,"BLK":12,"TOV":45,"PF":69,"PTS":379},{"PLAYER_ID":1631222,"SEASON_ID":"2024-25","LEAGUE_ID":"00","TEAM_ID":1610612763,"TEAM_ABBREVIATION":"MEM","PLAYER_AGE":23.0,"GP":47,"GS":0,"MIN":982,"FGM":118,"FGA":241,"FG_PCT":0.49,"FG3M":40,"FG3A":90,"FG3_PCT":0.444,"FTM":67,"FTA":96,"FT_PCT":0.698,"OREB":67,"DREB":138,"REB":205,"AST":133,"STL":44,"BLK":20,"TOV":69,"PF":92,"PTS":343},{"PLAYER_ID":1631222,"SEASON_ID":"2024-25","LEAGUE_ID":"00","TEAM_ID":1610612758,"TEAM_ABBREVIATION":"SAC","PLAYER_AGE":23.0,"GP":19,"GS":0,"MIN":367,"FGM":42,"FGA":96,"FG_PCT":0.438,"FG3M":20,"FG3A":52,"FG3_PCT":0.385,"FTM":11,"FTA":19,"FT_PCT":0.579,"OREB":23,"DREB":31,"REB":54,"AST":25,"STL":18,"BLK":3,"TOV":17,"PF":40,"PTS":115},{"PLAYER_ID":1631222,"SEASON_ID":"2025-26","LEAGUE_ID":"00","TEAM_ID":1610612747,"TEAM_ABBREVIATION":"LAL","PLAYER_AGE":24.0,"GP":30,"GS":9,"MIN":752,"FGM":95,"FGA":210,"FG_PCT":0.452,"FG3M":28,"FG3A":89,"FG3_PCT":0.315,"FTM":44,"FTA":62,"FT_PCT":0.71,"OREB":44,"DREB":80,"REB":124,"AST":59,"STL":37,"BLK":13,"TOV":32,"PF":68,"PTS":262}]