[{"PLAYER_ID":168,"SEASON_ID":"1993-94","LEAGUE_ID":"00","TEAM_ID":1610612739,"TEAM_ABBREVIATION":"CLE","PLAYER_AGE":24.0,"GP":79,"GS":18,"MIN":2022,"FGM":284,"FGA":677,"FG_PCT":0.419,"FG3M":38,"FG3A":122,"FG3_PCT":0.311,"FTM":137,"FTA":176,"FT_PCT":0.778,"OREB":134,"DREB":267,"REB":401,"AST":128,"STL":54,"BLK":50,"TOV":89,"PF":232,"PTS":743},{"PLAYER_ID":168,"SEASON_ID":"1994-95","LEAGUE_ID":"00","TEAM_ID":1610612739,"TEAM_ABBREVIATION":"CLE","PLAYER_AGE":25.0,"GP":80,"GS":79,"MIN":2814,"FGM":359,"FGA":855,"FG_PCT":0.42,"FG3M":94,"FG3A":240,"FG3_PCT":0.392,"FTM":174,"FTA":213,"FT_PCT":0.817,"OREB":99,"DREB":267,"REB":366,"AST":154,"STL":59,"BLK":35,"TOV":120,"PF":242,"PTS":986},{"PLAYER_ID":168,"SEASON_ID":"1995-96","LEAGUE_ID":"00","TEAM_ID":1610612739,"TEAM_ABBREVIATION":"CLE","PLAYER_AGE":26.0,"GP":80,"GS":80,"MIN":3060,"FGM":454,"FGA":971,"FG_PCT":0.468,"FG3M":79,"FG3A":210,"FG3_PCT":0.376,"FTM":218,"FTA":263,"FT_PCT":0.829,"OREB":112,"DREB":331,"REB":443,"AST":188,"STL":73,"BLK":52,"TOV":121,"PF":241,"PTS":1205},{"PLAYER_ID":168,"SEASON_ID":"1996-97","LEAGUE_ID":"00","TEAM_ID":1610612739,"TEAM_ABBREVIATION":"CLE","PLAYER_AGE":27.0,"GP":80,"GS":79,"MIN":3167,"FGM":405,"FGA":894,"FG_PCT":0.453,"FG3M":86,"FG3A":220,"FG3_PCT":0.391,"FTM":176,"FTA":209,"FT_PCT":0.842,"OREB":118,"DREB":379,"REB":497,"AST":198,"STL":86,"BLK":41,"TOV":120,"PF":222,"PTS":1072},{"PLAYER_ID":168,"SEASON_ID":"1997-98","LEAGUE_ID":"00","TEAM_ID":1610612752,"TEAM_ABBREVIATION":"NYK","PLAYER_AGE":28.0,"GP":80,"GS":29,"MIN":2183,"FGM":292,"FGA":675,"FG_PCT":0.433,"FG3M":40,"FG3A":137,"FG3_PCT":0.292,"FTM":152,"FTA":189,"FT_PCT":0.804,"OREB":120,"DREB":288,"REB":408,"AST":133,"STL":45,"BLK":30,"TOV":107,"PF":218,"PTS":776},{"PLAYER_ID":168,"SEASON_ID":"1998-99","LEAGUE_ID":"00","TEAM_ID":1610612744,"TEAM_ABBREVIATION":"GSW","PLAYER_AGE":29.0,"GP":47,"GS":24,"MIN":1395,"FGM":186,"FGA":453,"FG_PCT":0.411,"FG3M":32,"FG3A":115,"FG3_PCT":0.278,"FTM":79,"FTA":96,"FT_PCT":0.823,"OREB":49,"DREB":188,"REB":237,"AST":103,"STL":39,"BLK":14,"TOV":58,"PF":125,"PTS":483},{"PLAYER_ID":168,"SEASON_ID":"1999-00","LEAGUE_ID":"00","TEAM_ID":1610612744,"TEAM_ABBREVIATION":"GSW","PLAYER_AGE":30.0,"GP":20,"GS":11,"MIN":649,"FGM":123,"FGA":292,"FG_PCT":0.421,"FG3M":8,"FG3A":30,"FG3_PCT":0.267,"FTM":68,"FTA":84,"FT_PCT":0.81,"OREB":46,"DREB":77,"REB":123,"AST":47,"STL":18,"BLK":4,"TOV":25,"PF":60,"PTS":322},{"PLAYER_ID":168,"SEASON_ID":"2000-01","LEAGUE_ID":"00","TEAM_ID":1610612744,"TEAM_ABBREVIATION":"GSW","PLAYER_AGE":31.0,"GP":15,"GS":8,"MIN":493,"FGM":71,"FGA":191,"FG_PCT":0.372,"FG3M":7,"FG3A":25,"FG3_PCT":0.28,"FTM":31,"FTA":36,"FT_PCT":0.861,"OREB":24,"DREB":69,"REB":93,"AST":18,"STL":9,"BLK":5,"TOV":20,"PF":43,"PTS":180},{"PLAYER_ID":168,"SEASON_ID":"2001-02","LEAGUE_ID":"00","TEAM_ID":1610612744,"TEAM_ABBREVIATION":"GSW","PLAYER_AGE":32.0,"GP":66,"GS":0,"MIN":1236,"FGM":178,"FGA":427,"FG_PCT":0.417,"FG3M":48,"FG3A":127,"FG3_PCT":0.378,"FTM":85,"FTA":107,"FT_PCT":0.794,"OREB":51,"DREB":139,"REB":190,"AST":72,"STL":31,"BLK":13,"TOV":56,"PF":120,"PTS":489},{"PLAYER_ID":168,"SEASON_ID":"2002-03","LEAGUE_ID":"00","TEAM_ID":1610612744,"TEAM_ABBREVIATION":"GSW","PLAYER_AGE":33.0,"GP":21,"GS":0,"MIN":262,"FGM":39,"FGA":106,"FG_PCT":0.368,"FG3M":7,"FG3A":25,"FG3_PCT":0.28,"FTM":16,"FTA":18,"FT_PCT":0.889,"OREB":19,"DREB":31,"REB":50,"AST":22,"STL":7,"BLK":3,"TOV":10,"PF":29,"PTS":101}]