[{"PLAYER_ID":1717,"SEASON_ID":"1998-99","LEAGUE_ID":"00","TEAM_ID":1610612742,"TEAM_ABBREVIATION":"DAL","PLAYER_AGE":21.0,"GP":47,"GS":24,"MIN":958,"FGM":136,"FGA":336,"FG_PCT":0.405,"FG3M":14,"FG3A":68,"FG3_PCT":0.206,"FTM":99,"FTA":128,"FT_PCT":0.773,"OREB":41,"DREB":121,"REB":162,"AST":47,"STL":29,"BLK":27,"TOV":73,"PF":105,"PTS":385},{"PLAYER_ID":1717,"SEASON_ID":"1999-00","LEAGUE_ID":"00","TEAM_ID":1610612742,"TEAM_ABBREVIATION":"DAL","PLAYER_AGE":22.0,"GP":82,"GS":81,"MIN":2938,"FGM":515,"FGA":1118,"FG_PCT":0.461,"FG3M":116,"FG3A":306,"FG3_PCT":0.379,"FTM":289,"FTA":348,"FT_PCT":0.83,"OREB":102,"DREB":430,"REB":532,"AST":203,"STL":63,"BLK":68,"TOV":141,"PF":256,"PTS":1435},{"PLAYER_ID":1717,"SEASON_ID":"2000-01","LEAGUE_ID":"00","TEAM_ID":1610612742,"TEAM_ABBREVIATION":"DAL","PLAYER_AGE":23.0,"GP":82,"GS":82,"MIN":3125,"FGM":591,"FGA":1247,"FG_PCT":0.474,"FG3M":151,"FG3A":390,"FG3_PCT":0.387,"FTM":451,"FTA":538,"FT_PCT":0.838,"OREB":119,"DREB":635,"REB":754,"AST":173,"STL":79,"BLK":101,"TOV":156,"PF":245,"PTS":1784},{"PLAYER_ID":1717,"SEASON_ID":"2001-02","LEAGUE_ID":"00","TEAM_ID":1610612742,"TEAM_ABBREVIATION":"DAL","PLAYER_AGE":24.0,"GP":76,"GS":76,"MIN":2891,"FGM":600,"FGA":1258,"FG_PCT":0.477,"FG3M":139,"FG3A":350,"FG3_PCT":0.397,"FTM":440,"FTA":516,"FT_PCT":0.853,"OREB":120,"DREB":635,"REB":755,"AST":186,"STL":83,"BLK":77,"TOV":145,"PF":222,"PTS":1779},{"PLAYER_ID":1717,"SEASON_ID":"2002-03","LEAGUE_ID":"00","TEAM_ID":1610612742,"TEAM_ABBREVIATION":"DAL","PLAYER_AGE":25.0,"GP":80,"GS":80,"MIN":3117,"FGM":690,"FGA":1489,"FG_PCT":0.463,"FG3M":148,"FG3A":390,"FG3_PCT":0.379,"FTM":483,"FTA":548,"FT_PCT":0.881,"OREB":81,"DREB":710,"REB":791,"AST":239,"STL":111,"BLK":82,"TOV":152,"PF":206,"PTS":2011},{"PLAYER_ID":1717,"SEASON_ID":"2003-04","LEAGUE_ID":"00","TEAM_ID":1610612742,"TEAM_ABBREVIATION":"DAL","PLAYER_AGE":26.0,"GP":77,"GS":77,"MIN":2914,"FGM":605,"FGA":1310,"FG_PCT":0.462,"FG3M":99,"FG3A":290,"FG3_PCT":0.341,"FTM":371,"FTA":423,"FT_PCT":0.877,"OREB":90,"DREB":580,"REB":670,"AST":207,"STL":92,"BLK":104,"TOV":135,"PF":216,"PTS":1680},{"PLAYER_ID":1717,"SEASON_ID":"2004-05","LEAGUE_ID":"00","TEAM_ID":1610612742,"TEAM_ABBREVIATION":"DAL","PLAYER_AGE":27.0,"GP":78,"GS":78,"MIN":3020,"FGM":663,"FGA":1445,"FG_PCT":0.459,"FG3M":91,"FG3A":228,"FG3_PCT":0.399,"FTM":615,"FTA":708,"FT_PCT":0.869,"OREB":96,"DREB":661,"REB":757,"AST":240,"STL":97,"BLK":119,"TOV":176,"PF":219,"PTS":2032},{"PLAYER_ID":1717,"SEASON_ID":"2005-06","LEAGUE_ID":"00","TEAM_ID":1610612742,"TEAM_ABBREVIATION":"DAL","PLAYER_AGE":28.0,"GP":81,"GS":81,"MIN":3089,"FGM":751,"FGA":1564,"FG_PCT":0.48,"FG3M":110,"FG3A":271,"FG3_PCT":0.406,"FTM":539,"FTA":598,"FT_PCT":0.901,"OREB":115,"DREB":613,"REB":728,"AST":226,"STL":58,"BLK":83,"TOV":156,"PF":164,"PTS":2151},{"PLAYER_ID":1717,"SEASON_ID":"2006-07","LEAGUE_ID":"00","TEAM_ID":1610612742,"TEAM_ABBREVIATION":"DAL","PLAYER_AGE":29.0,"GP":78,"GS":78,"MIN":2820,"FGM":673,"FGA":1341,"FG_PCT":0.502,"FG3M":72,"FG3A":173,"FG3_PCT":0.416,"FTM":498,"FTA":551,"FT_PCT":0.904,"OREB":122,"DREB":571,"REB":693,"AST":263,"STL":52,"BLK":62,"TOV":167,"PF":171,"PTS":1916},{"PLAYER_ID":1717,"SEASON_ID":"2007-08","LEAGUE_ID":"00","TEAM_ID":1610612742,"TEAM_ABBREVIATION":"DAL","PLAYER_AGE":30.0,"GP":77,"GS":77,"MIN":2769,"FGM":630,"FGA":1314,"FG_PCT":0.479,"FG3M":79,"FG3A":220,"FG3_PCT":0.359,"FTM":478,"FTA":544,"FT_PCT":0.879,"OREB":95,"DREB":564,"REB":659,"AST":266,"STL":51,"BLK":71,"TOV":160,"PF":198,"PTS":1817},{"PLAYER_ID":1717,"SEASON_ID":"2008-09","LEAGUE_ID":"00","TEAM_ID":1610612742,"TEAM_ABBREVIATION":"DAL","PLAYER_AGE":31.0,"GP":81,"GS":81,"MIN":3050,"FGM":774,"FGA":1616,"FG_PCT":0.479,"FG3M":61,"FG3A":170,"FG3_PCT":0.359,"FTM":485,"FTA":545,"FT_PCT":0.89,"OREB":88,"DREB":593,"REB":681,"AST":197,"STL":61,"BLK":63,"TOV":157,"PF":176,"PTS":2094},{"PLAYER_ID":1717,"SEASON_ID":"2009-10","LEAGUE_ID":"00","TEAM_ID":1610612742,"TEAM_ABBREVIATION":"DAL","PLAYER_AGE":32.0,"GP":81,"GS":80,"MIN":3039,"FGM":720,"FGA":1496,"FG_PCT":0.481,"FG3M":51,"FG3A":121,"FG3_PCT":0.421,"FTM":536,"FTA":586,"FT_PCT":0.915,"OREB":80,"DREB":540,"REB":620,"AST":218,"STL":70,"BLK":79,"TOV":149,"PF":208,"PTS":2027},{"PLAYER_ID":1717,"SEASON_ID":"2010-11","LEAGUE_ID":"00","TEAM_ID":1610612742,"TEAM_ABBREVIATION":"DAL","PLAYER_AGE":33.0,"GP":73,"GS":73,"MIN":2504,"FGM":610,"FGA":1179,"FG_PCT":0.517,"FG3M":66,"FG3A":168,"FG3_PCT":0.393,"FTM":395,"FTA":443,"FT_PCT":0.892,"OREB":50,"DREB":463,"REB":513,"AST":190,"STL":38,"BLK":47,"TOV":137,"PF":172,"PTS":1681},{"PLAYER_ID":1717,"SEASON_ID":"2011-12","LEAGUE_ID":"00","TEAM_ID":1610612742,"TEAM_ABBREVIATION":"DAL","PLAYER_AGE":34.0,"GP":62,"GS":62,"MIN":2079,"FGM":473,"FGA":1034,"FG_PCT":0.457,"FG3M":78,"FG3A":212,"FG3_PCT":0.368,"FTM":318,"FTA":355,"FT_PCT":0.896,"OREB":46,"DREB":372,"REB":418,"AST":136,"STL":42,"BLK":30,"TOV":117,"PF":129,"PTS":1342},{"PLAYER_ID":1717,"SEASON_ID":"2012-13","LEAGUE_ID":"00","TEAM_ID":1610612742,"TEAM_ABBREVIATION":"DAL","PLAYER_AGE":35.0,"GP":53,"GS":47,"MIN":1661,"FGM":343,"FGA":728,"FG_PCT":0.471,"FG3M":65,"FG3A":157,"FG3_PCT":0.414,"FTM":166,"FTA":193,"FT_PCT":0.86,"OREB":37,"DREB":326,"REB":363,"AST":132,"STL":38,"BLK":37,"TOV":70,"PF":93,"PTS":917},{"PLAYER_ID":1717,"SEASON_ID":"2013-14","LEAGUE_ID":"00","TEAM_ID":1610612742,"TEAM_ABBREVIATION":"DAL","PLAYER_AGE":36.0,"GP":80,"GS":80,"MIN":2628,"FGM":633,"FGA":1273,"FG_PCT":0.497,"FG3M":131,"FG3A":329,"FG3_PCT":0.398,"FTM":338,"FTA":376,"FT_PCT":0.899,"OREB":40,"DREB":458,"REB":498,"AST":216,"STL":73,"BLK":45,"TOV":117,"PF":165,"PTS":1735},{"PLAYER_ID":1717,"SEASON_ID":"2014-15","LEAGUE_ID":"00","TEAM_ID":1610612742,"TEAM_ABBREVIATION":"DAL","PLAYER_AGE":37.0,"GP":77,"GS":77,"MIN":2282,"FGM":487,"FGA":1062,"FG_PCT":0.459,"FG3M":104,"FG3A":274,"FG3_PCT":0.38,"FTM":255,"FTA":289,"FT_PCT":0.882,"OREB":44,"DREB":413,"REB":457,"AST":143,"STL":39,"BLK":33,"TOV":82,"PF":160,"PTS":1333},{"PLAYER_ID":1717,"SEASON_ID":"2015-16","LEAGUE_ID":"00","TEAM_ID":1610612742,"TEAM_ABBREVIATION":"DAL","PLAYER_AGE":38.0,"GP":75,"GS":75,"MIN":2364,"FGM":498,"FGA":1112,"FG_PCT":0.448,"FG3M":126,"FG3A":342,"FG3_PCT":0.368,"FTM":250,"FTA":280,"FT_PCT":0.893,"OREB":52,"DREB":437,"REB":489,"AST":132,"STL":52,"BLK":52,"TOV":84,"PF":161,"PTS":1372},{"PLAYER_ID":1717,"SEASON_ID":"2016-17","LEAGUE_ID":"00","TEAM_ID":1610612742,"TEAM_ABBREVIATION":"DAL","PLAYER_AGE":39.0,"GP":54,"GS":54,"MIN":1424,"FGM":296,"FGA":678,"FG_PCT":0.437,"FG3M":79,"FG3A":209,"FG3_PCT":0.378,"FTM":98,"FTA":112,"FT_PCT":0.875,"OREB":23,"DREB":330,"REB":353,"AST":82,"STL":30,"BLK":38,"TOV":51,"PF":113,"PTS":769},{"PLAYER_ID":1717,"SEASON_ID":"2017-18","LEAGUE_ID":"00","TEAM_ID":1610612742,"TEAM_ABBREVIATION":"DAL","PLAYER_AGE":40.0,"GP":77,"GS":77,"MIN":1900,"FGM":346,"FGA":758,"FG_PCT":0.456,"FG3M":138,"FG3A":337,"FG3_PCT":0.409,"FTM":97,"FTA":108,"FT_PCT":0.898,"OREB":22,"DREB":416,"REB":438,"AST":120,"STL":43,"BLK":45,"TOV":51,"PF":146,"PTS":927},{"PLAYER_ID":1717,"SEASON_ID":"2018-19","LEAGUE_ID":"00","TEAM_ID":1610612742,"TEAM_ABBREVIATION":"DAL","PLAYER_AGE":41.0,"GP":51,"GS":20,"MIN":795,"FGM":135,"FGA":376,"FG_PCT":0.359,"FG3M":64,"FG3A":205,"FG3_PCT":0.312,"FTM":39,"FTA":50,"FT_PCT":0.78,"OREB":5,"DREB":153,"REB":158,"AST":35,"STL":9,"BLK":18,"TOV":18,"PF":76,"PTS":373}]