[{"PLAYER_ID":203115,"SEASON_ID":"2012-13","LEAGUE_ID":"00","TEAM_ID":1610612757,"TEAM_ABBREVIATION":"POR","PLAYER_AGE":22.0,"GP":73,"GS":5,"MIN":894,"FGM":118,"FGA":309,"FG_PCT":0.382,"FG3M":9,"FG3A":65,"FG3_PCT":0.138,"FTM":50,"FTA":65,"FT_PCT":0.769,"OREB":36,"DREB":109,"REB":145,"AST":58,"STL":34,"BLK":9,"TOV":60,"PF":56,"PTS":295},{"PLAYER_ID":203115,"SEASON_ID":"2013-14","LEAGUE_ID":"00","TEAM_ID":1610612757,"TEAM_ABBREVIATION":"POR","PLAYER_AGE":23.0,"GP":41,"GS":0,"MIN":387,"FGM":65,"FGA":156,"FG_PCT":0.417,"FG3M":10,"FG3A":33,"FG3_PCT":0.303,"FTM":26,"FTA":32,"FT_PCT":0.813,"OREB":16,"DREB":58,"REB":74,"AST":33,"STL":9,"BLK":7,"TOV":18,"PF":31,"PTS":166},{"PLAYER_ID":203115,"SEASON_ID":"2014-15","LEAGUE_ID":"00","TEAM_ID":1610612757,"TEAM_ABBREVIATION":"POR","PLAYER_AGE":24.0,"GP":30,"GS":0,"MIN":300,"FGM":38,"FGA":100,"FG_PCT":0.38,"FG3M":4,"FG3A":18,"FG3_PCT":0.222,"FTM":10,"FTA":15,"FT_PCT":0.667,"OREB":3,"DREB":31,"REB":34,"AST":27,"STL":14,"BLK":4,"TOV":17,"PF":20,"PTS":90},{"PLAYER_ID":203115,"SEASON_ID":"2014-15","LEAGUE_ID":"00","TEAM_ID":1610612743,"TEAM_ABBREVIATION":"DEN","PLAYER_AGE":24.0,"GP":28,"GS":0,"MIN":683,"FGM":112,"FGA":253,"FG_PCT":0.443,"FG3M":19,"FG3A":67,"FG3_PCT":0.284,"FTM":64,"FTA":79,"FT_PCT":0.81,"OREB":23,"DREB":105,"REB":128,"AST":54,"STL":34,"BLK":15,"TOV":44,"PF":50,"PTS":307},{"PLAYER_ID":203115,"SEASON_ID":"2015-16","LEAGUE_ID":"00","TEAM_ID":1610612743,"TEAM_ABBREVIATION":"DEN","PLAYER_AGE":25.0,"GP":82,"GS":1,"MIN":2353,"FGM":425,"FGA":983,"FG_PCT":0.432,"FG3M":112,"FG3A":325,"FG3_PCT":0.345,"FTM":216,"FTA":268,"FT_PCT":0.806,"OREB":59,"DREB":417,"REB":476,"AST":203,"STL":71,"BLK":39,"TOV":139,"PF":147,"PTS":1178},{"PLAYER_ID":203115,"SEASON_ID":"2016-17","LEAGUE_ID":"00","TEAM_ID":1610612743,"TEAM_ABBREVIATION":"DEN","PLAYER_AGE":26.0,"GP":60,"GS":19,"MIN":1705,"FGM":295,"FGA":666,"FG_PCT":0.443,"FG3M":87,"FG3A":235,"FG3_PCT":0.37,"FTM":143,"FTA":190,"FT_PCT":0.753,"OREB":58,"DREB":201,"REB":259,"AST":206,"STL":48,"BLK":28,"TOV":97,"PF":110,"PTS":820},{"PLAYER_ID":203115,"SEASON_ID":"2017-18","LEAGUE_ID":"00","TEAM_ID":1610612743,"TEAM_ABBREVIATION":"DEN","PLAYER_AGE":27.0,"GP":81,"GS":40,"MIN":2683,"FGM":465,"FGA":1028,"FG_PCT":0.452,"FG3M":156,"FG3A":422,"FG3_PCT":0.37,"FTM":182,"FTA":226,"FT_PCT":0.805,"OREB":70,"DREB":339,"REB":409,"AST":331,"STL":82,"BLK":52,"TOV":149,"PF":168,"PTS":1268},{"PLAYER_ID":203115,"SEASON_ID":"2018-19","LEAGUE_ID":"00","TEAM_ID":1610612743,"TEAM_ABBREVIATION":"DEN","PLAYER_AGE":28.0,"GP":43,"GS":38,"MIN":1189,"FGM":185,"FGA":460,"FG_PCT":0.402,"FG3M":67,"FG3A":196,"FG3_PCT":0.342,"FTM":57,"FTA":74,"FT_PCT":0.77,"OREB":32,"DREB":167,"REB":199,"AST":124,"STL":18,"BLK":22,"TOV":65,"PF":82,"PTS":494},{"PLAYER_ID":203115,"SEASON_ID":"2019-20","LEAGUE_ID":"00","TEAM_ID":1610612743,"TEAM_ABBREVIATION":"DEN","PLAYER_AGE":29.0,"GP":58,"GS":58,"MIN":1916,"FGM":332,"FGA":738,"FG_PCT":0.45,"FG3M":108,"FG3A":288,"FG3_PCT":0.375,"FTM":102,"FTA":133,"FT_PCT":0.767,"OREB":76,"DREB":289,"REB":365,"AST":212,"STL":61,"BLK":29,"TOV":88,"PF":121,"PTS":874},{"PLAYER_ID":203115,"SEASON_ID":"2020-21","LEAGUE_ID":"00","TEAM_ID":1610612743,"TEAM_ABBREVIATION":"DEN","PLAYER_AGE":30.0,"GP":56,"GS":52,"MIN":1736,"FGM":259,"FGA":608,"FG_PCT":0.426,"FG3M":98,"FG3A":257,"FG3_PCT":0.381,"FTM":95,"FTA":121,"FT_PCT":0.785,"OREB":39,"DREB":187,"REB":226,"AST":181,"STL":50,"BLK":23,"TOV":96,"PF":95,"PTS":711},{"PLAYER_ID":203115,"SEASON_ID":"2021-22","LEAGUE_ID":"00","TEAM_ID":1610612743,"TEAM_ABBREVIATION":"DEN","PLAYER_AGE":31.0,"GP":71,"GS":71,"MIN":2276,"FGM":392,"FGA":896,"FG_PCT":0.438,"FG3M":157,"FG3A":430,"FG3_PCT":0.365,"FTM":102,"FTA":127,"FT_PCT":0.803,"OREB":44,"DREB":296,"REB":340,"AST":276,"STL":55,"BLK":31,"TOV":127,"PF":114,"PTS":1043},{"PLAYER_ID":203115,"SEASON_ID":"2022-23","LEAGUE_ID":"00","TEAM_ID":1610612764,"TEAM_ABBREVIATION":"WAS","PLAYER_AGE":32.0,"GP":40,"GS":0,"MIN":782,"FGM":110,"FGA":285,"FG_PCT":0.386,"FG3M":52,"FG3A":138,"FG3_PCT":0.377,"FTM":35,"FTA":45,"FT_PCT":0.778,"OREB":10,"DREB":101,"REB":111,"AST":95,"STL":17,"BLK":10,"TOV":45,"PF":39,"PTS":307},{"PLAYER_ID":203115,"SEASON_ID":"2022-23","LEAGUE_ID":"00","TEAM_ID":1610612761,"TEAM_ABBREVIATION":"TOR","PLAYER_AGE":32.0,"GP":16,"GS":2,"MIN":211,"FGM":28,"FGA":79,"FG_PCT":0.354,"FG3M":14,"FG3A":42,"FG3_PCT":0.333,"FTM":2,"FTA":2,"FT_PCT":1.0,"OREB":5,"DREB":21,"REB":26,"AST":17,"STL":11,"BLK":3,"TOV":3,"PF":17,"PTS":72}]