[{"PLAYER_ID":2063,"SEASON_ID":"2000-01","LEAGUE_ID":"00","TEAM_ID":1610612741,"TEAM_ABBREVIATION":"CHI","PLAYER_AGE":23.0,"GP":16,"GS":2,"MIN":143,"FGM":11,"FGA":25,"FG_PCT":0.44,"FG3M":0,"FG3A":0,"FG3_PCT":0.0,"FTM":8,"FTA":14,"FT_PCT":0.571,"OREB":12,"DREB":22,"REB":34,"AST":5,"STL":5,"BLK":6,"TOV":12,"PF":38,"PTS":30},{"PLAYER_ID":2063,"SEASON_ID":"2001-02","LEAGUE_ID":"00","TEAM_ID":1610612756,"TEAM_ABBREVIATION":"PHX","PLAYER_AGE":24.0,"GP":59,"GS":34,"MIN":901,"FGM":107,"FGA":193,"FG_PCT":0.554,"FG3M":0,"FG3A":0,"FG3_PCT":0.0,"FTM":82,"FTA":109,"FT_PCT":0.752,"OREB":103,"DREB":147,"REB":250,"AST":18,"STL":11,"BLK":23,"TOV":48,"PF":139,"PTS":296},{"PLAYER_ID":2063,"SEASON_ID":"2002-03","LEAGUE_ID":"00","TEAM_ID":1610612756,"TEAM_ABBREVIATION":"PHX","PLAYER_AGE":25.0,"GP":65,"GS":1,"MIN":947,"FGM":92,"FGA":163,"FG_PCT":0.564,"FG3M":0,"FG3A":0,"FG3_PCT":0.0,"FTM":64,"FTA":96,"FT_PCT":0.667,"OREB":97,"DREB":128,"REB":225,"AST":36,"STL":18,"BLK":29,"TOV":48,"PF":172,"PTS":248},{"PLAYER_ID":2063,"SEASON_ID":"2003-04","LEAGUE_ID":"00","TEAM_ID":1610612756,"TEAM_ABBREVIATION":"PHX","PLAYER_AGE":26.0,"GP":66,"GS":43,"MIN":1601,"FGM":152,"FGA":300,"FG_PCT":0.507,"FG3M":0,"FG3A":0,"FG3_PCT":0.0,"FTM":134,"FTA":181,"FT_PCT":0.74,"OREB":123,"DREB":220,"REB":343,"AST":57,"STL":42,"BLK":25,"TOV":77,"PF":258,"PTS":438},{"PLAYER_ID":2063,"SEASON_ID":"2004-05","LEAGUE_ID":"00","TEAM_ID":1610612756,"TEAM_ABBREVIATION":"PHX","PLAYER_AGE":27.0,"GP":38,"GS":1,"MIN":360,"FGM":27,"FGA":59,"FG_PCT":0.458,"FG3M":0,"FG3A":0,"FG3_PCT":0.0,"FTM":26,"FTA":38,"FT_PCT":0.684,"OREB":30,"DREB":62,"REB":92,"AST":17,"STL":4,"BLK":11,"TOV":20,"PF":60,"PTS":80},{"PLAYER_ID":2063,"SEASON_ID":"2005-06","LEAGUE_ID":"00","TEAM_ID":1610612766,"TEAM_ABBREVIATION":"CHA","PLAYER_AGE":28.0,"GP":51,"GS":2,"MIN":818,"FGM":114,"FGA":261,"FG_PCT":0.437,"FG3M":1,"FG3A":3,"FG3_PCT":0.333,"FTM":41,"FTA":60,"FT_PCT":0.683,"OREB":62,"DREB":121,"REB":183,"AST":39,"STL":26,"BLK":23,"TOV":33,"PF":157,"PTS":270},{"PLAYER_ID":2063,"SEASON_ID":"2006-07","LEAGUE_ID":"00","TEAM_ID":1610612766,"TEAM_ABBREVIATION":"CHA","PLAYER_AGE":29.0,"GP":73,"GS":9,"MIN":1043,"FGM":121,"FGA":255,"FG_PCT":0.475,"FG3M":0,"FG3A":0,"FG3_PCT":0.0,"FTM":77,"FTA":113,"FT_PCT":0.681,"OREB":84,"DREB":172,"REB":256,"AST":44,"STL":30,"BLK":24,"TOV":56,"PF":199,"PTS":319},{"PLAYER_ID":2063,"SEASON_ID":"2007-08","LEAGUE_ID":"00","TEAM_ID":1610612749,"TEAM_ABBREVIATION":"MIL","PLAYER_AGE":30.0,"GP":44,"GS":0,"MIN":386,"FGM":37,"FGA":80,"FG_PCT":0.463,"FG3M":0,"FG3A":0,"FG3_PCT":0.0,"FTM":24,"FTA":29,"FT_PCT":0.828,"OREB":30,"DREB":67,"REB":97,"AST":13,"STL":9,"BLK":21,"TOV":29,"PF":83,"PTS":98},{"PLAYER_ID":2063,"SEASON_ID":"2008-09","LEAGUE_ID":"00","TEAM_ID":1610612761,"TEAM_ABBREVIATION":"TOR","PLAYER_AGE":31.0,"GP":38,"GS":1,"MIN":240,"FGM":12,"FGA":45,"FG_PCT":0.267,"FG3M":0,"FG3A":0,"FG3_PCT":0.0,"FTM":11,"FTA":14,"FT_PCT":0.786,"OREB":21,"DREB":38,"REB":59,"AST":8,"STL":3,"BLK":4,"TOV":17,"PF":60,"PTS":35}]