[{"PLAYER_ID":431,"SEASON_ID":"1989-90","LEAGUE_ID":"00","TEAM_ID":1610612760,"TEAM_ABBREVIATION":"SEA","PLAYER_AGE":20.0,"GP":81,"GS":1,"MIN":1120,"FGM":203,"FGA":424,"FG_PCT":0.479,"FG3M":2,"FG3A":12,"FG3_PCT":0.167,"FTM":117,"FTA":159,"FT_PCT":0.736,"OREB":146,"DREB":200,"REB":346,"AST":26,"STL":47,"BLK":70,"TOV":107,"PF":204,"PTS":525},{"PLAYER_ID":431,"SEASON_ID":"1990-91","LEAGUE_ID":"00","TEAM_ID":1610612760,"TEAM_ABBREVIATION":"SEA","PLAYER_AGE":21.0,"GP":81,"GS":66,"MIN":2442,"FGM":462,"FGA":909,"FG_PCT":0.508,"FG3M":2,"FG3A":12,"FG3_PCT":0.167,"FTM":288,"FTA":436,"FT_PCT":0.661,"OREB":267,"DREB":412,"REB":679,"AST":144,"STL":77,"BLK":123,"TOV":202,"PF":319,"PTS":1214},{"PLAYER_ID":431,"SEASON_ID":"1991-92","LEAGUE_ID":"00","TEAM_ID":1610612760,"TEAM_ABBREVIATION":"SEA","PLAYER_AGE":22.0,"GP":64,"GS":23,"MIN":1808,"FGM":362,"FGA":718,"FG_PCT":0.504,"FG3M":0,"FG3A":3,"FG3_PCT":0.0,"FTM":270,"FTA":361,"FT_PCT":0.748,"OREB":264,"DREB":401,"REB":665,"AST":86,"STL":70,"BLK":124,"TOV":156,"PF":261,"PTS":994},{"PLAYER_ID":431,"SEASON_ID":"1992-93","LEAGUE_ID":"00","TEAM_ID":1610612760,"TEAM_ABBREVIATION":"SEA","PLAYER_AGE":23.0,"GP":78,"GS":68,"MIN":2582,"FGM":515,"FGA":1047,"FG_PCT":0.492,"FG3M":0,"FG3A":4,"FG3_PCT":0.0,"FTM":358,"FTA":503,"FT_PCT":0.712,"OREB":287,"DREB":546,"REB":833,"AST":155,"STL":119,"BLK":146,"TOV":217,"PF":327,"PTS":1388},{"PLAYER_ID":431,"SEASON_ID":"1993-94","LEAGUE_ID":"00","TEAM_ID":1610612760,"TEAM_ABBREVIATION":"SEA","PLAYER_AGE":24.0,"GP":79,"GS":73,"MIN":2597,"FGM":533,"FGA":990,"FG_PCT":0.538,"FG3M":1,"FG3A":4,"FG3_PCT":0.25,"FTM":364,"FTA":491,"FT_PCT":0.741,"OREB":312,"DREB":539,"REB":851,"AST":207,"STL":142,"BLK":166,"TOV":259,"PF":312,"PTS":1431},{"PLAYER_ID":431,"SEASON_ID":"1994-95","LEAGUE_ID":"00","TEAM_ID":1610612760,"TEAM_ABBREVIATION":"SEA","PLAYER_AGE":25.0,"GP":82,"GS":79,"MIN":2679,"FGM":545,"FGA":997,"FG_PCT":0.547,"FG3M":2,"FG3A":7,"FG3_PCT":0.286,"FTM":438,"FTA":585,"FT_PCT":0.749,"OREB":318,"DREB":575,"REB":893,"AST":149,"STL":102,"BLK":122,"TOV":259,"PF":337,"PTS":1530},{"PLAYER_ID":431,"SEASON_ID":"1995-96","LEAGUE_ID":"00","TEAM_ID":1610612760,"TEAM_ABBREVIATION":"SEA","PLAYER_AGE":26.0,"GP":79,"GS":76,"MIN":2631,"FGM":526,"FGA":937,"FG_PCT":0.561,"FG3M":5,"FG3A":12,"FG3_PCT":0.417,"FTM":493,"FTA":664,"FT_PCT":0.742,"OREB":276,"DREB":628,"REB":904,"AST":173,"STL":93,"BLK":127,"TOV":315,"PF":299,"PTS":1550},{"PLAYER_ID":431,"SEASON_ID":"1996-97","LEAGUE_ID":"00","TEAM_ID":1610612760,"TEAM_ABBREVIATION":"SEA","PLAYER_AGE":27.0,"GP":81,"GS":73,"MIN":2753,"FGM":526,"FGA":1032,"FG_PCT":0.51,"FG3M":12,"FG3A":33,"FG3_PCT":0.364,"FTM":452,"FTA":609,"FT_PCT":0.742,"OREB":275,"DREB":532,"REB":807,"AST":156,"STL":125,"BLK":81,"TOV":280,"PF":320,"PTS":1516},{"PLAYER_ID":431,"SEASON_ID":"1997-98","LEAGUE_ID":"00","TEAM_ID":1610612739,"TEAM_ABBREVIATION":"CLE","PLAYER_AGE":28.0,"GP":80,"GS":80,"MIN":2769,"FGM":518,"FGA":1164,"FG_PCT":0.445,"FG3M":2,"FG3A":8,"FG3_PCT":0.25,"FTM":404,"FTA":556,"FT_PCT":0.727,"OREB":219,"DREB":526,"REB":745,"AST":197,"STL":108,"BLK":90,"TOV":271,"PF":310,"PTS":1442},{"PLAYER_ID":431,"SEASON_ID":"1998-99","LEAGUE_ID":"00","TEAM_ID":1610612739,"TEAM_ABBREVIATION":"CLE","PLAYER_AGE":29.0,"GP":42,"GS":42,"MIN":1475,"FGM":277,"FGA":575,"FG_PCT":0.482,"FG3M":1,"FG3A":2,"FG3_PCT":0.5,"FTM":307,"FTA":389,"FT_PCT":0.789,"OREB":131,"DREB":257,"REB":388,"AST":101,"STL":48,"BLK":45,"TOV":127,"PF":159,"PTS":862},{"PLAYER_ID":431,"SEASON_ID":"1999-00","LEAGUE_ID":"00","TEAM_ID":1610612739,"TEAM_ABBREVIATION":"CLE","PLAYER_AGE":30.0,"GP":82,"GS":82,"MIN":2492,"FGM":484,"FGA":1160,"FG_PCT":0.417,"FG3M":2,"FG3A":6,"FG3_PCT":0.333,"FTM":493,"FTA":635,"FT_PCT":0.776,"OREB":231,"DREB":494,"REB":725,"AST":138,"STL":100,"BLK":96,"TOV":291,"PF":371,"PTS":1463},{"PLAYER_ID":431,"SEASON_ID":"2000-01","LEAGUE_ID":"00","TEAM_ID":1610612757,"TEAM_ABBREVIATION":"POR","PLAYER_AGE":31.0,"GP":68,"GS":3,"MIN":1083,"FGM":168,"FGA":413,"FG_PCT":0.407,"FG3M":4,"FG3A":11,"FG3_PCT":0.364,"FTM":101,"FTA":131,"FT_PCT":0.771,"OREB":63,"DREB":196,"REB":259,"AST":65,"STL":45,"BLK":23,"TOV":99,"PF":184,"PTS":441},{"PLAYER_ID":431,"SEASON_ID":"2001-02","LEAGUE_ID":"00","TEAM_ID":1610612757,"TEAM_ABBREVIATION":"POR","PLAYER_AGE":32.0,"GP":75,"GS":5,"MIN":1235,"FGM":175,"FGA":407,"FG_PCT":0.43,"FG3M":0,"FG3A":4,"FG3_PCT":0.0,"FTM":104,"FTA":131,"FT_PCT":0.794,"OREB":90,"DREB":198,"REB":288,"AST":52,"STL":43,"BLK":33,"TOV":81,"PF":184,"PTS":454},{"PLAYER_ID":431,"SEASON_ID":"2002-03","LEAGUE_ID":"00","TEAM_ID":1610612753,"TEAM_ABBREVIATION":"ORL","PLAYER_AGE":33.0,"GP":79,"GS":55,"MIN":1633,"FGM":211,"FGA":505,"FG_PCT":0.418,"FG3M":0,"FG3A":1,"FG3_PCT":0.0,"FTM":115,"FTA":155,"FT_PCT":0.742,"OREB":147,"DREB":304,"REB":451,"AST":55,"STL":66,"BLK":33,"TOV":102,"PF":239,"PTS":537}]