[{"PLAYER_ID":76137,"SEASON_ID":"1946-47","LEAGUE_ID":"00","TEAM_ID":1610610031,"TEAM_ABBREVIATION":"PIT","PLAYER_AGE":30.0,"GP":17,"GS":null,"MIN":0.0,"FGM":46,"FGA":229,"FG_PCT":0.201,"FG3M":null,"FG3A":null,"FG3_PCT":null,"FTM":16,"FTA":30,"FT_PCT":0.533,"OREB":null,"DREB":null,"REB":0.0,"AST":14,"STL":null,"BLK":null,"TOV":null,"PF":50,"PTS":108},{"PLAYER_ID":76137,"SEASON_ID":"1946-47","LEAGUE_ID":"00","TEAM_ID":1610612738,"TEAM_ABBREVIATION":"BOS","PLAYER_AGE":30.0,"GP":6,"GS":null,"MIN":0.0,"FGM":5,"FGA":22,"FG_PCT":0.227,"FG3M":null,"FG3A":null,"FG3_PCT":null,"FTM":3,"FTA":4,"FT_PCT":0.75,"OREB":null,"DREB":null,"REB":0.0,"AST":1,"STL":null,"BLK":null,"TOV":null,"PF":15,"PTS":13},{"PLAYER_ID":76137,"SEASON_ID":"1946-47","LEAGUE_ID":"00","TEAM_ID":1610610028,"TEAM_ABBREVIATION":"DEF","PLAYER_AGE":30.0,"GP":20,"GS":null,"MIN":0.0,"FGM":19,"FGA":107,"FG_PCT":0.178,"FG3M":null,"FG3A":null,"FG3_PCT":null,"FTM":3,"FTA":10,"FT_PCT":0.3,"OREB":null,"DREB":null,"REB":0.0,"AST":15,"STL":null,"BLK":null,"TOV":null,"PF":33,"PTS":41}]