[{"PLAYER_ID":76954,"SEASON_ID":"1980-81","LEAGUE_ID":"00","TEAM_ID":1610612757,"TEAM_ABBREVIATION":"POR","PLAYER_AGE":23.0,"GP":55,"GS":null,"MIN":461,"FGM":56,"FGA":136,"FG_PCT":0.412,"FG3M":0,"FG3A":3,"FG3_PCT":0.0,"FTM":37,"FTA":85,"FT_PCT":0.435,"OREB":28,"DREB":65,"REB":93,"AST":17,"STL":23,"BLK":20,"TOV":32,"PF":73,"PTS":149},{"PLAYER_ID":76954,"SEASON_ID":"1981-82","LEAGUE_ID":"00","TEAM_ID":1610612757,"TEAM_ABBREVIATION":"POR","PLAYER_AGE":24.0,"GP":68,"GS":38.0,"MIN":1433,"FGM":184,"FGA":370,"FG_PCT":0.497,"FG3M":0,"FG3A":1,"FG3_PCT":0.0,"FTM":96,"FTA":153,"FT_PCT":0.627,"OREB":127,"DREB":212,"REB":339,"AST":54,"STL":55,"BLK":82,"TOV":92,"PF":229,"PTS":464}]