[{"PLAYER_ID":77087,"SEASON_ID":"1979-80","LEAGUE_ID":"00","TEAM_ID":1610612752,"TEAM_ABBREVIATION":"NYK","PLAYER_AGE":22.0,"GP":71,"GS":null,"MIN":923,"FGM":94,"FGA":241,"FG_PCT":0.39,"FG3M":3,"FG3A":17,"FG3_PCT":0.176,"FTM":28,"FTA":38,"FT_PCT":0.737,"OREB":14,"DREB":44,"REB":58,"AST":159,"STL":39,"BLK":5,"TOV":73,"PF":83,"PTS":219},{"PLAYER_ID":77087,"SEASON_ID":"1980-81","LEAGUE_ID":"00","TEAM_ID":1610612742,"TEAM_ABBREVIATION":"DAL","PLAYER_AGE":23.0,"GP":56,"GS":null,"MIN":1892,"FGM":385,"FGA":789,"FG_PCT":0.488,"FG3M":1,"FG3A":4,"FG3_PCT":0.25,"FTM":128,"FTA":185,"FT_PCT":0.692,"OREB":33,"DREB":66,"REB":99,"AST":277,"STL":45,"BLK":6,"TOV":148,"PF":113,"PTS":899},{"PLAYER_ID":77087,"SEASON_ID":"1980-81","LEAGUE_ID":"00","TEAM_ID":1610612739,"TEAM_ABBREVIATION":"CLE","PLAYER_AGE":23.0,"GP":25,"GS":null,"MIN":542,"FGM":76,"FGA":153,"FG_PCT":0.497,"FG3M":0,"FG3A":1,"FG3_PCT":0.0,"FTM":22,"FTA":27,"FT_PCT":0.815,"OREB":12,"DREB":27,"REB":39,"AST":117,"STL":13,"BLK":1,"TOV":31,"PF":35,"PTS":174},{"PLAYER_ID":77087,"SEASON_ID":"1981-82","LEAGUE_ID":"00","TEAM_ID":1610612739,"TEAM_ABBREVIATION":"CLE","PLAYER_AGE":24.0,"GP":78,"GS":43.0,"MIN":2409,"FGM":325,"FGA":672,"FG_PCT":0.484,"FG3M":3,"FG3A":10,"FG3_PCT":0.3,"FTM":153,"FTA":200,"FT_PCT":0.765,"OREB":53,"DREB":97,"REB":150,"AST":590,"STL":70,"BLK":11,"TOV":171,"PF":169,"PTS":806},{"PLAYER_ID":77087,"SEASON_ID":"1982-83","LEAGUE_ID":"00","TEAM_ID":1610612739,"TEAM_ABBREVIATION":"CLE","PLAYER_AGE":25.0,"GP":80,"GS":79.0,"MIN":2716,"FGM":401,"FGA":832,"FG_PCT":0.482,"FG3M":4,"FG3A":12,"FG3_PCT":0.333,"FTM":168,"FTA":245,"FT_PCT":0.686,"OREB":41,"DREB":118,"REB":159,"AST":487,"STL":74,"BLK":4,"TOV":195,"PF":215,"PTS":974},{"PLAYER_ID":77087,"SEASON_ID":"1983-84","LEAGUE_ID":"00","TEAM_ID":1610612739,"TEAM_ABBREVIATION":"CLE","PLAYER_AGE":26.0,"GP":77,"GS":56.0,"MIN":2041,"FGM":348,"FGA":699,"FG_PCT":0.498,"FG3M":2,"FG3A":11,"FG3_PCT":0.182,"FTM":110,"FTA":154,"FT_PCT":0.714,"OREB":32,"DREB":64,"REB":96,"AST":413,"STL":38,"BLK":1,"TOV":145,"PF":126,"PTS":808},{"PLAYER_ID":77087,"SEASON_ID":"1984-85","LEAGUE_ID":"00","TEAM_ID":1610612739,"TEAM_ABBREVIATION":"CLE","PLAYER_AGE":27.0,"GP":8,"GS":0.0,"MIN":93,"FGM":12,"FGA":25,"FG_PCT":0.48,"FG3M":0,"FG3A":0,"FG3_PCT":null,"FTM":2,"FTA":3,"FT_PCT":0.667,"OREB":0,"DREB":1,"REB":1,"AST":23,"STL":0,"BLK":0,"TOV":8,"PF":8,"PTS":26},{"PLAYER_ID":77087,"SEASON_ID":"1985-86","LEAGUE_ID":"00","TEAM_ID":1610612744,"TEAM_ABBREVIATION":"GOS","PLAYER_AGE":28.0,"GP":82,"GS":0.0,"MIN":1208,"FGM":140,"FGA":273,"FG_PCT":0.513,"FG3M":2,"FG3A":6,"FG3_PCT":0.333,"FTM":63,"FTA":92,"FT_PCT":0.685,"OREB":10,"DREB":55,"REB":65,"AST":342,"STL":38,"BLK":4,"TOV":83,"PF":67,"PTS":345},{"PLAYER_ID":77087,"SEASON_ID":"1986-87","LEAGUE_ID":"00","TEAM_ID":1610612746,"TEAM_ABBREVIATION":"LAC","PLAYER_AGE":29.0,"GP":19,"GS":8.0,"MIN":428,"FGM":55,"FGA":121,"FG_PCT":0.455,"FG3M":1,"FG3A":2,"FG3_PCT":0.5,"FTM":18,"FTA":34,"FT_PCT":0.529,"OREB":6,"DREB":11,"REB":17,"AST":101,"STL":14,"BLK":0,"TOV":45,"PF":28,"PTS":129}]