[{"PLAYER_ID":77195,"SEASON_ID":"1967-68","LEAGUE_ID":"00","TEAM_ID":1610612745,"TEAM_ABBREVIATION":"SDR","PLAYER_AGE":23.0,"GP":42,"GS":null,"MIN":603,"FGM":86,"FGA":232,"FG_PCT":0.371,"FG3M":null,"FG3A":null,"FG3_PCT":null,"FTM":55,"FTA":69,"FT_PCT":0.797,"OREB":null,"DREB":null,"REB":67,"AST":89,"STL":null,"BLK":null,"TOV":null,"PF":84,"PTS":227},{"PLAYER_ID":77195,"SEASON_ID":"1970-71","LEAGUE_ID":"00","TEAM_ID":1610612744,"TEAM_ABBREVIATION":"SFW","PLAYER_AGE":26.0,"GP":81,"GS":null,"MIN":1183,"FGM":225,"FGA":523,"FG_PCT":0.43,"FG3M":null,"FG3A":null,"FG3_PCT":null,"FTM":111,"FTA":151,"FT_PCT":0.735,"OREB":null,"DREB":null,"REB":110,"AST":113,"STL":null,"BLK":null,"TOV":null,"PF":192,"PTS":561},{"PLAYER_ID":77195,"SEASON_ID":"1971-72","LEAGUE_ID":"00","TEAM_ID":1610612744,"TEAM_ABBREVIATION":"GOS","PLAYER_AGE":27.0,"GP":65,"GS":null,"MIN":478,"FGM":82,"FGA":196,"FG_PCT":0.418,"FG3M":null,"FG3A":null,"FG3_PCT":null,"FTM":51,"FTA":61,"FT_PCT":0.836,"OREB":null,"DREB":null,"REB":39,"AST":45,"STL":null,"BLK":null,"TOV":null,"PF":109,"PTS":215}]