[{"PLAYER_ID":77338,"SEASON_ID":"1968-69","LEAGUE_ID":"00","TEAM_ID":1610612745,"TEAM_ABBREVIATION":"SDR","PLAYER_AGE":22.0,"GP":73,"GS":null,"MIN":1378,"FGM":220,"FGA":482,"FG_PCT":0.456,"FG3M":null,"FG3A":null,"FG3_PCT":null,"FTM":129,"FTA":167,"FT_PCT":0.772,"OREB":null,"DREB":null,"REB":236,"AST":99,"STL":null,"BLK":null,"TOV":null,"PF":178,"PTS":569},{"PLAYER_ID":77338,"SEASON_ID":"1969-70","LEAGUE_ID":"00","TEAM_ID":1610612745,"TEAM_ABBREVIATION":"SDR","PLAYER_AGE":23.0,"GP":82,"GS":null,"MIN":2471,"FGM":455,"FGA":1027,"FG_PCT":0.443,"FG3M":null,"FG3A":null,"FG3_PCT":null,"FTM":278,"FTA":361,"FT_PCT":0.77,"OREB":null,"DREB":null,"REB":255,"AST":287,"STL":null,"BLK":null,"TOV":null,"PF":238,"PTS":1188},{"PLAYER_ID":77338,"SEASON_ID":"1970-71","LEAGUE_ID":"00","TEAM_ID":1610612745,"TEAM_ABBREVIATION":"SDR","PLAYER_AGE":24.0,"GP":82,"GS":null,"MIN":3102,"FGM":585,"FGA":1305,"FG_PCT":0.448,"FG3M":null,"FG3A":null,"FG3_PCT":null,"FTM":519,"FTA":644,"FT_PCT":0.806,"OREB":null,"DREB":null,"REB":406,"AST":344,"STL":null,"BLK":null,"TOV":null,"PF":230,"PTS":1689},{"PLAYER_ID":77338,"SEASON_ID":"1971-72","LEAGUE_ID":"00","TEAM_ID":1610612745,"TEAM_ABBREVIATION":"HOU","PLAYER_AGE":25.0,"GP":81,"GS":null,"MIN":3097,"FGM":557,"FGA":1279,"FG_PCT":0.435,"FG3M":null,"FG3A":null,"FG3_PCT":null,"FTM":387,"FTA":462,"FT_PCT":0.838,"OREB":null,"DREB":null,"REB":345,"AST":337,"STL":null,"BLK":null,"TOV":null,"PF":211,"PTS":1501},{"PLAYER_ID":77338,"SEASON_ID":"1972-73","LEAGUE_ID":"00","TEAM_ID":1610612765,"TEAM_ABBREVIATION":"DET","PLAYER_AGE":26.0,"GP":51,"GS":null,"MIN":1603,"FGM":185,"FGA":455,"FG_PCT":0.407,"FG3M":null,"FG3A":null,"FG3_PCT":null,"FTM":120,"FTA":150,"FT_PCT":0.8,"OREB":null,"DREB":null,"REB":172,"AST":138,"STL":null,"BLK":null,"TOV":null,"PF":117,"PTS":490},{"PLAYER_ID":77338,"SEASON_ID":"1973-74","LEAGUE_ID":"00","TEAM_ID":1610612765,"TEAM_ABBREVIATION":"DET","PLAYER_AGE":27.0,"GP":50,"GS":null,"MIN":980,"FGM":154,"FGA":361,"FG_PCT":0.427,"FG3M":null,"FG3A":null,"FG3_PCT":null,"FTM":139,"FTA":164,"FT_PCT":0.848,"OREB":34.0,"DREB":79.0,"REB":113,"AST":97,"STL":38.0,"BLK":3.0,"TOV":null,"PF":79,"PTS":447},{"PLAYER_ID":77338,"SEASON_ID":"1974-75","LEAGUE_ID":"00","TEAM_ID":1610612762,"TEAM_ABBREVIATION":"NOJ","PLAYER_AGE":28.0,"GP":19,"GS":null,"MIN":353,"FGM":39,"FGA":115,"FG_PCT":0.339,"FG3M":null,"FG3A":null,"FG3_PCT":null,"FTM":47,"FTA":53,"FT_PCT":0.887,"OREB":7.0,"DREB":17.0,"REB":24,"AST":30,"STL":12.0,"BLK":2.0,"TOV":null,"PF":28,"PTS":125},{"PLAYER_ID":77338,"SEASON_ID":"1974-75","LEAGUE_ID":"00","TEAM_ID":1610612747,"TEAM_ABBREVIATION":"LAL","PLAYER_AGE":28.0,"GP":56,"GS":null,"MIN":1430,"FGM":189,"FGA":446,"FG_PCT":0.424,"FG3M":null,"FG3A":null,"FG3_PCT":null,"FTM":145,"FTA":176,"FT_PCT":0.824,"OREB":81.0,"DREB":89.0,"REB":170,"AST":158,"STL":44.0,"BLK":10.0,"TOV":null,"PF":134,"PTS":523},{"PLAYER_ID":77338,"SEASON_ID":"1975-76","LEAGUE_ID":"00","TEAM_ID":1610612747,"TEAM_ABBREVIATION":"LAL","PLAYER_AGE":29.0,"GP":53,"GS":null,"MIN":853,"FGM":85,"FGA":204,"FG_PCT":0.417,"FG3M":null,"FG3A":null,"FG3_PCT":null,"FTM":80,"FTA":89,"FT_PCT":0.899,"OREB":28.0,"DREB":71.0,"REB":99,"AST":76,"STL":27.0,"BLK":3.0,"TOV":null,"PF":105,"PTS":250}]