[{"PLAYER_ID":77435,"SEASON_ID":"1981-82","LEAGUE_ID":"00","TEAM_ID":1610612737,"TEAM_ABBREVIATION":"ATL","PLAYER_AGE":24.0,"GP":79,"GS":32,"MIN":1516,"FGM":210,"FGA":484,"FG_PCT":0.434,"FG3M":0,"FG3A":3,"FG3_PCT":0.0,"FTM":134,"FTA":173,"FT_PCT":0.775,"OREB":113,"DREB":150,"REB":263,"AST":47,"STL":40,"BLK":20,"TOV":112,"PF":225,"PTS":554},{"PLAYER_ID":77435,"SEASON_ID":"1982-83","LEAGUE_ID":"00","TEAM_ID":1610612737,"TEAM_ABBREVIATION":"ATL","PLAYER_AGE":25.0,"GP":73,"GS":20,"MIN":1171,"FGM":170,"FGA":360,"FG_PCT":0.472,"FG3M":0,"FG3A":4,"FG3_PCT":0.0,"FTM":101,"FTA":131,"FT_PCT":0.771,"OREB":85,"DREB":105,"REB":190,"AST":71,"STL":41,"BLK":10,"TOV":89,"PF":189,"PTS":441},{"PLAYER_ID":77435,"SEASON_ID":"1983-84","LEAGUE_ID":"00","TEAM_ID":1610612752,"TEAM_ABBREVIATION":"NYK","PLAYER_AGE":26.0,"GP":8,"GS":0,"MIN":65,"FGM":12,"FGA":30,"FG_PCT":0.4,"FG3M":0,"FG3A":0,"FG3_PCT":0.0,"FTM":11,"FTA":13,"FT_PCT":0.846,"OREB":5,"DREB":6,"REB":11,"AST":3,"STL":1,"BLK":0,"TOV":6,"PF":17,"PTS":35}]