[{"PLAYER_ID":77480,"SEASON_ID":"1949-50","LEAGUE_ID":"00","TEAM_ID":1610612747,"TEAM_ABBREVIATION":"MNL","PLAYER_AGE":24.0,"GP":67,"GS":null,"MIN":null,"FGM":106,"FGA":302,"FG_PCT":0.351,"FG3M":null,"FG3A":null,"FG3_PCT":null,"FTM":59,"FTA":93,"FT_PCT":0.634,"OREB":null,"DREB":null,"REB":null,"AST":148,"STL":null,"BLK":null,"TOV":null,"PF":162,"PTS":271},{"PLAYER_ID":77480,"SEASON_ID":"1950-51","LEAGUE_ID":"00","TEAM_ID":1610612747,"TEAM_ABBREVIATION":"MNL","PLAYER_AGE":25.0,"GP":68,"GS":null,"MIN":null,"FGM":227,"FGA":627,"FG_PCT":0.362,"FG3M":null,"FG3A":null,"FG3_PCT":null,"FTM":121,"FTA":177,"FT_PCT":0.684,"OREB":null,"DREB":null,"REB":246.0,"AST":235,"STL":null,"BLK":null,"TOV":null,"PF":199,"PTS":575},{"PLAYER_ID":77480,"SEASON_ID":"1951-52","LEAGUE_ID":"00","TEAM_ID":1610612747,"TEAM_ABBREVIATION":"MNL","PLAYER_AGE":26.0,"GP":66,"GS":null,"MIN":2480.0,"FGM":237,"FGA":632,"FG_PCT":0.375,"FG3M":null,"FG3A":null,"FG3_PCT":null,"FTM":142,"FTA":190,"FT_PCT":0.747,"OREB":null,"DREB":null,"REB":228.0,"AST":249,"STL":null,"BLK":null,"TOV":null,"PF":226,"PTS":616},{"PLAYER_ID":77480,"SEASON_ID":"1952-53","LEAGUE_ID":"00","TEAM_ID":1610612747,"TEAM_ABBREVIATION":"MNL","PLAYER_AGE":27.0,"GP":70,"GS":null,"MIN":2556.0,"FGM":260,"FGA":634,"FG_PCT":0.41,"FG3M":null,"FG3A":null,"FG3_PCT":null,"FTM":224,"FTA":287,"FT_PCT":0.78,"OREB":null,"DREB":null,"REB":186.0,"AST":250,"STL":null,"BLK":null,"TOV":null,"PF":246,"PTS":744},{"PLAYER_ID":77480,"SEASON_ID":"1953-54","LEAGUE_ID":"00","TEAM_ID":1610612747,"TEAM_ABBREVIATION":"MNL","PLAYER_AGE":28.0,"GP":69,"GS":null,"MIN":2472.0,"FGM":254,"FGA":654,"FG_PCT":0.388,"FG3M":null,"FG3A":null,"FG3_PCT":null,"FTM":176,"FTA":243,"FT_PCT":0.724,"OREB":null,"DREB":null,"REB":166.0,"AST":253,"STL":null,"BLK":null,"TOV":null,"PF":198,"PTS":684},{"PLAYER_ID":77480,"SEASON_ID":"1954-55","LEAGUE_ID":"00","TEAM_ID":1610612747,"TEAM_ABBREVIATION":"MNL","PLAYER_AGE":29.0,"GP":72,"GS":null,"MIN":2784.0,"FGM":350,"FGA":919,"FG_PCT":0.381,"FG3M":null,"FG3A":null,"FG3_PCT":null,"FTM":276,"FTA":359,"FT_PCT":0.769,"OREB":null,"DREB":null,"REB":260.0,"AST":427,"STL":null,"BLK":null,"TOV":null,"PF":221,"PTS":976},{"PLAYER_ID":77480,"SEASON_ID":"1955-56","LEAGUE_ID":"00","TEAM_ID":1610612747,"TEAM_ABBREVIATION":"MNL","PLAYER_AGE":30.0,"GP":72,"GS":null,"MIN":2838.0,"FGM":309,"FGA":863,"FG_PCT":0.358,"FG3M":null,"FG3A":null,"FG3_PCT":null,"FTM":329,"FTA":395,"FT_PCT":0.833,"OREB":null,"DREB":null,"REB":260.0,"AST":445,"STL":null,"BLK":null,"TOV":null,"PF":202,"PTS":947},{"PLAYER_ID":77480,"SEASON_ID":"1956-57","LEAGUE_ID":"00","TEAM_ID":1610612737,"TEAM_ABBREVIATION":"STL","PLAYER_AGE":31.0,"GP":66,"GS":null,"MIN":2401.0,"FGM":244,"FGA":736,"FG_PCT":0.332,"FG3M":null,"FG3A":null,"FG3_PCT":null,"FTM":230,"FTA":291,"FT_PCT":0.79,"OREB":null,"DREB":null,"REB":288.0,"AST":269,"STL":null,"BLK":null,"TOV":null,"PF":193,"PTS":718},{"PLAYER_ID":77480,"SEASON_ID":"1957-58","LEAGUE_ID":"00","TEAM_ID":1610612737,"TEAM_ABBREVIATION":"STL","PLAYER_AGE":32.0,"GP":60,"GS":null,"MIN":2098.0,"FGM":258,"FGA":768,"FG_PCT":0.336,"FG3M":null,"FG3A":null,"FG3_PCT":null,"FTM":206,"FTA":276,"FT_PCT":0.746,"OREB":null,"DREB":null,"REB":228.0,"AST":218,"STL":null,"BLK":null,"TOV":null,"PF":187,"PTS":722},{"PLAYER_ID":77480,"SEASON_ID":"1958-59","LEAGUE_ID":"00","TEAM_ID":1610612737,"TEAM_ABBREVIATION":"STL","PLAYER_AGE":33.0,"GP":71,"GS":null,"MIN":2504.0,"FGM":245,"FGA":706,"FG_PCT":0.347,"FG3M":null,"FG3A":null,"FG3_PCT":null,"FTM":197,"FTA":254,"FT_PCT":0.776,"OREB":null,"DREB":null,"REB":253.0,"AST":336,"STL":null,"BLK":null,"TOV":null,"PF":230,"PTS":687},{"PLAYER_ID":77480,"SEASON_ID":"1959-60","LEAGUE_ID":"00","TEAM_ID":1610612737,"TEAM_ABBREVIATION":"STL","PLAYER_AGE":34.0,"GP":64,"GS":null,"MIN":1756.0,"FGM":142,"FGA":383,"FG_PCT":0.371,"FG3M":null,"FG3A":null,"FG3_PCT":null,"FTM":113,"FTA":155,"FT_PCT":0.729,"OREB":null,"DREB":null,"REB":187.0,"AST":330,"STL":null,"BLK":null,"TOV":null,"PF":174,"PTS":397}]