[{"PLAYER_ID":77536,"SEASON_ID":"1951-52","LEAGUE_ID":"00","TEAM_ID":1610612752,"TEAM_ABBREVIATION":"NYK","PLAYER_AGE":23.0,"GP":59,"GS":null,"MIN":788,"FGM":72,"FGA":167,"FG_PCT":0.431,"FG3M":null,"FG3A":null,"FG3_PCT":null,"FTM":64,"FTA":122,"FT_PCT":0.525,"OREB":null,"DREB":null,"REB":121,"AST":107,"STL":null,"BLK":null,"TOV":null,"PF":136,"PTS":208},{"PLAYER_ID":77536,"SEASON_ID":"1952-53","LEAGUE_ID":"00","TEAM_ID":1610612752,"TEAM_ABBREVIATION":"NYK","PLAYER_AGE":24.0,"GP":58,"GS":null,"MIN":1231,"FGM":112,"FGA":287,"FG_PCT":0.39,"FG3M":null,"FG3A":null,"FG3_PCT":null,"FTM":128,"FTA":201,"FT_PCT":0.637,"OREB":null,"DREB":null,"REB":167,"AST":145,"STL":null,"BLK":null,"TOV":null,"PF":206,"PTS":352},{"PLAYER_ID":77536,"SEASON_ID":"1953-54","LEAGUE_ID":"00","TEAM_ID":1610612752,"TEAM_ABBREVIATION":"NYK","PLAYER_AGE":25.0,"GP":64,"GS":null,"MIN":849,"FGM":58,"FGA":177,"FG_PCT":0.328,"FG3M":null,"FG3A":null,"FG3_PCT":null,"FTM":58,"FTA":133,"FT_PCT":0.436,"OREB":null,"DREB":null,"REB":121,"AST":103,"STL":null,"BLK":null,"TOV":null,"PF":144,"PTS":174},{"PLAYER_ID":77536,"SEASON_ID":"1954-55","LEAGUE_ID":"00","TEAM_ID":1610610024,"TEAM_ABBREVIATION":"BAL","PLAYER_AGE":26.0,"GP":10,"GS":null,"MIN":98,"FGM":9,"FGA":32,"FG_PCT":0.281,"FG3M":null,"FG3A":null,"FG3_PCT":null,"FTM":5,"FTA":7,"FT_PCT":0.714,"OREB":null,"DREB":null,"REB":9,"AST":8,"STL":null,"BLK":null,"TOV":null,"PF":15,"PTS":23}]