[{"PLAYER_ID":78579,"SEASON_ID":"1964-65","LEAGUE_ID":"00","TEAM_ID":1610612758,"TEAM_ABBREVIATION":"CIN","PLAYER_AGE":23.0,"GP":39,"GS":null,"MIN":288,"FGM":41,"FGA":155,"FG_PCT":0.265,"FG3M":null,"FG3A":null,"FG3_PCT":null,"FTM":9,"FTA":30,"FT_PCT":0.3,"OREB":null,"DREB":null,"REB":102,"AST":11,"STL":null,"BLK":null,"TOV":null,"PF":59,"PTS":91},{"PLAYER_ID":78579,"SEASON_ID":"1965-66","LEAGUE_ID":"00","TEAM_ID":1610612758,"TEAM_ABBREVIATION":"CIN","PLAYER_AGE":24.0,"GP":47,"GS":null,"MIN":276,"FGM":54,"FGA":138,"FG_PCT":0.391,"FG3M":null,"FG3A":null,"FG3_PCT":null,"FTM":27,"FTA":42,"FT_PCT":0.643,"OREB":null,"DREB":null,"REB":98,"AST":17,"STL":null,"BLK":null,"TOV":null,"PF":56,"PTS":135},{"PLAYER_ID":78579,"SEASON_ID":"1966-67","LEAGUE_ID":"00","TEAM_ID":1610612741,"TEAM_ABBREVIATION":"CHI","PLAYER_AGE":25.0,"GP":43,"GS":null,"MIN":448,"FGM":77,"FGA":193,"FG_PCT":0.399,"FG3M":null,"FG3A":null,"FG3_PCT":null,"FTM":45,"FTA":70,"FT_PCT":0.643,"OREB":null,"DREB":null,"REB":163,"AST":15,"STL":null,"BLK":null,"TOV":null,"PF":73,"PTS":199},{"PLAYER_ID":78579,"SEASON_ID":"1966-67","LEAGUE_ID":"00","TEAM_ID":1610612758,"TEAM_ABBREVIATION":"CIN","PLAYER_AGE":25.0,"GP":12,"GS":null,"MIN":125,"FGM":8,"FGA":41,"FG_PCT":0.195,"FG3M":null,"FG3A":null,"FG3_PCT":null,"FTM":13,"FTA":16,"FT_PCT":0.813,"OREB":null,"DREB":null,"REB":43,"AST":0,"STL":null,"BLK":null,"TOV":null,"PF":19,"PTS":29},{"PLAYER_ID":78579,"SEASON_ID":"1967-68","LEAGUE_ID":"00","TEAM_ID":1610612760,"TEAM_ABBREVIATION":"SEA","PLAYER_AGE":26.0,"GP":77,"GS":null,"MIN":1236,"FGM":179,"FGA":498,"FG_PCT":0.359,"FG3M":null,"FG3A":null,"FG3_PCT":null,"FTM":109,"FTA":155,"FT_PCT":0.703,"OREB":null,"DREB":null,"REB":470,"AST":56,"STL":null,"BLK":null,"TOV":null,"PF":218,"PTS":467},{"PLAYER_ID":78579,"SEASON_ID":"1968-69","LEAGUE_ID":"00","TEAM_ID":1610612755,"TEAM_ABBREVIATION":"PHL","PLAYER_AGE":27.0,"GP":38,"GS":null,"MIN":552,"FGM":81,"FGA":182,"FG_PCT":0.445,"FG3M":null,"FG3A":null,"FG3_PCT":null,"FTM":60,"FTA":84,"FT_PCT":0.714,"OREB":null,"DREB":null,"REB":216,"AST":32,"STL":null,"BLK":null,"TOV":null,"PF":87,"PTS":222},{"PLAYER_ID":78579,"SEASON_ID":"1968-69","LEAGUE_ID":"00","TEAM_ID":1610612756,"TEAM_ABBREVIATION":"PHX","PLAYER_AGE":27.0,"GP":41,"GS":null,"MIN":1294,"FGM":191,"FGA":481,"FG_PCT":0.397,"FG3M":null,"FG3A":null,"FG3_PCT":null,"FTM":93,"FTA":151,"FT_PCT":0.616,"OREB":null,"DREB":null,"REB":505,"AST":76,"STL":null,"BLK":null,"TOV":null,"PF":145,"PTS":475},{"PLAYER_ID":78579,"SEASON_ID":"1969-70","LEAGUE_ID":"00","TEAM_ID":1610612755,"TEAM_ABBREVIATION":"PHL","PLAYER_AGE":28.0,"GP":67,"GS":null,"MIN":836,"FGM":118,"FGA":304,"FG_PCT":0.388,"FG3M":null,"FG3A":null,"FG3_PCT":null,"FTM":122,"FTA":172,"FT_PCT":0.709,"OREB":null,"DREB":null,"REB":317,"AST":52,"STL":null,"BLK":null,"TOV":null,"PF":145,"PTS":358},{"PLAYER_ID":78579,"SEASON_ID":"1970-71","LEAGUE_ID":"00","TEAM_ID":1610612746,"TEAM_ABBREVIATION":"BUF","PLAYER_AGE":29.0,"GP":46,"GS":null,"MIN":713,"FGM":92,"FGA":269,"FG_PCT":0.342,"FG3M":null,"FG3A":null,"FG3_PCT":null,"FTM":56,"FTA":69,"FT_PCT":0.812,"OREB":null,"DREB":null,"REB":230,"AST":48,"STL":null,"BLK":null,"TOV":null,"PF":99,"PTS":240}]