[{"PLAYER_ID":894,"SEASON_ID":"1982-83","LEAGUE_ID":"00","TEAM_ID":1610612765,"TEAM_ABBREVIATION":"DET","PLAYER_AGE":23.0,"GP":39,"GS":1,"MIN":265,"FGM":33,"FGA":88,"FG_PCT":0.375,"FG3M":1,"FG3A":7,"FG3_PCT":0.143,"FTM":18,"FTA":32,"FT_PCT":0.563,"OREB":15,"DREB":20,"REB":35,"AST":14,"STL":8,"BLK":4,"TOV":18,"PF":42,"PTS":85},{"PLAYER_ID":894,"SEASON_ID":"1983-84","LEAGUE_ID":"00","TEAM_ID":1610612746,"TEAM_ABBREVIATION":"SDC","PLAYER_AGE":24.0,"GP":69,"GS":35,"MIN":1280,"FGM":268,"FGA":570,"FG_PCT":0.47,"FG3M":0,"FG3A":9,"FG3_PCT":0.0,"FTM":149,"FTA":173,"FT_PCT":0.861,"OREB":59,"DREB":76,"REB":135,"AST":60,"STL":27,"BLK":13,"TOV":81,"PF":143,"PTS":685},{"PLAYER_ID":894,"SEASON_ID":"1984-85","LEAGUE_ID":"00","TEAM_ID":1610612749,"TEAM_ABBREVIATION":"MIL","PLAYER_AGE":25.0,"GP":44,"GS":3,"MIN":882,"FGM":165,"FGA":307,"FG_PCT":0.537,"FG3M":1,"FG3A":4,"FG3_PCT":0.25,"FTM":102,"FTA":124,"FT_PCT":0.823,"OREB":49,"DREB":68,"REB":117,"AST":94,"STL":34,"BLK":5,"TOV":63,"PF":117,"PTS":433},{"PLAYER_ID":894,"SEASON_ID":"1985-86","LEAGUE_ID":"00","TEAM_ID":1610612749,"TEAM_ABBREVIATION":"MIL","PLAYER_AGE":26.0,"GP":81,"GS":8,"MIN":2147,"FGM":429,"FGA":798,"FG_PCT":0.538,"FG3M":3,"FG3A":23,"FG3_PCT":0.13,"FTM":266,"FTA":310,"FT_PCT":0.858,"OREB":94,"DREB":137,"REB":231,"AST":177,"STL":83,"BLK":6,"TOV":107,"PF":252,"PTS":1127},{"PLAYER_ID":894,"SEASON_ID":"1986-87","LEAGUE_ID":"00","TEAM_ID":1610612749,"TEAM_ABBREVIATION":"MIL","PLAYER_AGE":27.0,"GP":79,"GS":31,"MIN":2505,"FGM":575,"FGA":1077,"FG_PCT":0.534,"FG3M":3,"FG3A":28,"FG3_PCT":0.107,"FTM":387,"FTA":440,"FT_PCT":0.88,"OREB":117,"DREB":149,"REB":266,"AST":144,"STL":64,"BLK":24,"TOV":120,"PF":222,"PTS":1540},{"PLAYER_ID":894,"SEASON_ID":"1987-88","LEAGUE_ID":"00","TEAM_ID":1610612749,"TEAM_ABBREVIATION":"MIL","PLAYER_AGE":28.0,"GP":37,"GS":0,"MIN":965,"FGM":248,"FGA":486,"FG_PCT":0.51,"FG3M":3,"FG3A":14,"FG3_PCT":0.214,"FTM":107,"FTA":122,"FT_PCT":0.877,"OREB":30,"DREB":53,"REB":83,"AST":73,"STL":21,"BLK":7,"TOV":57,"PF":94,"PTS":606},{"PLAYER_ID":894,"SEASON_ID":"1988-89","LEAGUE_ID":"00","TEAM_ID":1610612749,"TEAM_ABBREVIATION":"MIL","PLAYER_AGE":29.0,"GP":75,"GS":4,"MIN":2078,"FGM":527,"FGA":1018,"FG_PCT":0.518,"FG3M":8,"FG3A":36,"FG3_PCT":0.222,"FTM":255,"FTA":297,"FT_PCT":0.859,"OREB":82,"DREB":115,"REB":197,"AST":156,"STL":77,"BLK":19,"TOV":112,"PF":193,"PTS":1317},{"PLAYER_ID":894,"SEASON_ID":"1989-90","LEAGUE_ID":"00","TEAM_ID":1610612749,"TEAM_ABBREVIATION":"MIL","PLAYER_AGE":30.0,"GP":59,"GS":0,"MIN":1709,"FGM":503,"FGA":987,"FG_PCT":0.51,"FG3M":46,"FG3A":133,"FG3_PCT":0.346,"FTM":307,"FTA":366,"FT_PCT":0.839,"OREB":64,"DREB":103,"REB":167,"AST":133,"STL":50,"BLK":7,"TOV":129,"PF":158,"PTS":1359},{"PLAYER_ID":894,"SEASON_ID":"1990-91","LEAGUE_ID":"00","TEAM_ID":1610612749,"TEAM_ABBREVIATION":"MIL","PLAYER_AGE":31.0,"GP":46,"GS":0,"MIN":1327,"FGM":359,"FGA":720,"FG_PCT":0.499,"FG3M":37,"FG3A":93,"FG3_PCT":0.398,"FTM":282,"FTA":311,"FT_PCT":0.907,"OREB":37,"DREB":80,"REB":117,"AST":96,"STL":38,"BLK":11,"TOV":93,"PF":90,"PTS":1037},{"PLAYER_ID":894,"SEASON_ID":"1990-91","LEAGUE_ID":"00","TEAM_ID":1610612760,"TEAM_ABBREVIATION":"SEA","PLAYER_AGE":31.0,"GP":32,"GS":2,"MIN":840,"FGM":202,"FGA":436,"FG_PCT":0.463,"FG3M":9,"FG3A":23,"FG3_PCT":0.391,"FTM":148,"FTA":160,"FT_PCT":0.925,"OREB":30,"DREB":44,"REB":74,"AST":72,"STL":22,"BLK":2,"TOV":54,"PF":80,"PTS":561},{"PLAYER_ID":894,"SEASON_ID":"1991-92","LEAGUE_ID":"00","TEAM_ID":1610612760,"TEAM_ABBREVIATION":"SEA","PLAYER_AGE":32.0,"GP":78,"GS":78,"MIN":2658,"FGM":620,"FGA":1306,"FG_PCT":0.475,"FG3M":33,"FG3A":123,"FG3_PCT":0.268,"FTM":417,"FTA":455,"FT_PCT":0.916,"OREB":93,"DREB":140,"REB":233,"AST":241,"STL":86,"BLK":20,"TOV":189,"PF":213,"PTS":1690},{"PLAYER_ID":894,"SEASON_ID":"1992-93","LEAGUE_ID":"00","TEAM_ID":1610612760,"TEAM_ABBREVIATION":"SEA","PLAYER_AGE":33.0,"GP":77,"GS":72,"MIN":2218,"FGM":524,"FGA":1071,"FG_PCT":0.489,"FG3M":42,"FG3A":113,"FG3_PCT":0.372,"FTM":313,"FTA":352,"FT_PCT":0.889,"OREB":58,"DREB":134,"REB":192,"AST":220,"STL":100,"BLK":7,"TOV":160,"PF":167,"PTS":1403},{"PLAYER_ID":894,"SEASON_ID":"1993-94","LEAGUE_ID":"00","TEAM_ID":1610612760,"TEAM_ABBREVIATION":"SEA","PLAYER_AGE":34.0,"GP":51,"GS":0,"MIN":1022,"FGM":272,"FGA":577,"FG_PCT":0.471,"FG3M":6,"FG3A":32,"FG3_PCT":0.188,"FTM":189,"FTA":211,"FT_PCT":0.896,"OREB":29,"DREB":54,"REB":83,"AST":91,"STL":42,"BLK":5,"TOV":64,"PF":84,"PTS":739},{"PLAYER_ID":894,"SEASON_ID":"1994-95","LEAGUE_ID":"00","TEAM_ID":1610612744,"TEAM_ABBREVIATION":"GOS","PLAYER_AGE":35.0,"GP":27,"GS":6,"MIN":673,"FGM":111,"FGA":254,"FG_PCT":0.437,"FG3M":23,"FG3A":70,"FG3_PCT":0.329,"FTM":93,"FTA":106,"FT_PCT":0.877,"OREB":12,"DREB":52,"REB":64,"AST":40,"STL":22,"BLK":2,"TOV":24,"PF":38,"PTS":338},{"PLAYER_ID":894,"SEASON_ID":"1995-96","LEAGUE_ID":"00","TEAM_ID":1610612754,"TEAM_ABBREVIATION":"IND","PLAYER_AGE":36.0,"GP":76,"GS":2,"MIN":1404,"FGM":264,"FGA":590,"FG_PCT":0.447,"FG3M":35,"FG3A":104,"FG3_PCT":0.337,"FTM":174,"FTA":205,"FT_PCT":0.849,"OREB":40,"DREB":96,"REB":136,"AST":101,"STL":57,"BLK":6,"TOV":93,"PF":188,"PTS":737},{"PLAYER_ID":894,"SEASON_ID":"1996-97","LEAGUE_ID":"00","TEAM_ID":1610612743,"TEAM_ABBREVIATION":"DEN","PLAYER_AGE":37.0,"GP":33,"GS":10,"MIN":601,"FGM":120,"FGA":260,"FG_PCT":0.462,"FG3M":12,"FG3A":39,"FG3_PCT":0.308,"FTM":83,"FTA":92,"FT_PCT":0.902,"OREB":17,"DREB":36,"REB":53,"AST":31,"STL":14,"BLK":5,"TOV":38,"PF":49,"PTS":335},{"PLAYER_ID":894,"SEASON_ID":"1996-97","LEAGUE_ID":"00","TEAM_ID":1610612766,"TEAM_ABBREVIATION":"CHH","PLAYER_AGE":37.0,"GP":27,"GS":17,"MIN":653,"FGM":119,"FGA":237,"FG_PCT":0.502,"FG3M":30,"FG3A":56,"FG3_PCT":0.536,"FTM":56,"FTA":63,"FT_PCT":0.889,"OREB":19,"DREB":49,"REB":68,"AST":49,"STL":14,"BLK":4,"TOV":30,"PF":48,"PTS":324},{"PLAYER_ID":894,"SEASON_ID":"1997-98","LEAGUE_ID":"00","TEAM_ID":1610612749,"TEAM_ABBREVIATION":"MIL","PLAYER_AGE":38.0,"GP":39,"GS":0,"MIN":442,"FGM":52,"FGA":143,"FG_PCT":0.364,"FG3M":4,"FG3A":13,"FG3_PCT":0.308,"FTM":43,"FTA":52,"FT_PCT":0.827,"OREB":19,"DREB":26,"REB":45,"AST":34,"STL":9,"BLK":0,"TOV":21,"PF":35,"PTS":151}]